glcsweb/__init__.py
glcsweb/admin.py
glcsweb/apps.py
glcsweb/forms.py
glcsweb/models.py
glcsweb/serializer.py
glcsweb/tests.py
glcsweb/urls.py
glcsweb/views.py
glcsweb/static/bootstrap/css/bootstrap-grid.css
glcsweb/static/bootstrap/css/bootstrap-grid.css.map
glcsweb/static/bootstrap/css/bootstrap-grid.min.css
glcsweb/static/bootstrap/css/bootstrap-grid.min.css.map
glcsweb/static/bootstrap/css/bootstrap-reboot.css
glcsweb/static/bootstrap/css/bootstrap-reboot.css.map
glcsweb/static/bootstrap/css/bootstrap-reboot.min.css
glcsweb/static/bootstrap/css/bootstrap-reboot.min.css.map
glcsweb/static/bootstrap/css/bootstrap.css
glcsweb/static/bootstrap/css/bootstrap.css.map
glcsweb/static/bootstrap/css/bootstrap.min.css
glcsweb/static/bootstrap/css/bootstrap.min.css.map
glcsweb/static/bootstrap/js/bootstrap.bundle.js
glcsweb/static/bootstrap/js/bootstrap.bundle.js.map
glcsweb/static/bootstrap/js/bootstrap.bundle.min.js
glcsweb/static/bootstrap/js/bootstrap.bundle.min.js.map
glcsweb/static/bootstrap/js/bootstrap.js
glcsweb/static/bootstrap/js/bootstrap.js.map
glcsweb/static/bootstrap/js/bootstrap.min.js
glcsweb/static/bootstrap/js/bootstrap.min.js.map
glcsweb/static/web/css/main.css
glcsweb/templates/web/assignments.html
glcsweb/templates/web/course.html
glcsweb/templates/web/index.html
glcsweb/templates/web/signup.html
glcsweb/templates/web/student.html
glcsweb/templates/web/ta.html
glcsweb/templates/web/components/base.html
glcsweb/templates/web/components/content-header.html
glcsweb/templates/web/components/left-nav.html
glcsweb/templates/web/modules/add-course.html
glcsweb/templates/web/modules/add-credentials.html
glcsweb/templates/web/modules/assignment-list.html
glcsweb/templates/web/modules/assignment-overview.html
glcsweb/templates/web/modules/course-overview.html
django_glcsweb-0.1.5.dist-info/LICENSE
django_glcsweb-0.1.5.dist-info/METADATA
django_glcsweb-0.1.5.dist-info/WHEEL
django_glcsweb-0.1.5.dist-info/top_level.txt
django_glcsweb-0.1.5.dist-info/RECORD
