Metadata-Version: 2.1
Name: django-glcsweb
Version: 0.1.5
Summary: A Django app to provide a web interface for the glcs package
Home-page: UNKNOWN
Author: Austin Fishbaugh
Author-email: austin.fishbaugh@gmail.com
License: MIT License
Platform: UNKNOWN
Classifier: Environment :: Web Environment
Classifier: Framework :: Django
Classifier: Framework :: Django :: 2.2
Classifier: Intended Audience :: Developers
Classifier: License :: OSI Approved :: MIT License
Classifier: Operating System :: OS Independent
Classifier: Programming Language :: Python
Classifier: Programming Language :: Python :: 3.5
Classifier: Programming Language :: Python :: 3.6
Classifier: Topic :: Internet :: WWW/HTTP
Classifier: Topic :: Internet :: WWW/HTTP :: Dynamic Content
Requires-Dist: glcs
Requires-Dist: django
Requires-Dist: mysqlclient
